badcode/__init__.py
badcode-0.1.dist-info/METADATA
badcode-0.1.dist-info/WHEEL
badcode-0.1.dist-info/top_level.txt
badcode-0.1.dist-info/RECORD
