Metadata-Version: 2.1
Name: badcode
Version: 0.1
Summary: badcode place holder
Home-page: https://github.com/kirankotari/badcode
Author: Kiran Kumar Kotari
Author-email: kirankotari@live.com
License: UNKNOWN
Keywords: badcode,badcode-mutable,badcode-immutable
Platform: UNKNOWN
Classifier: Development Status :: 3 - Alpha
Classifier: Intended Audience :: Developers
Classifier: Topic :: Software Development :: Build Tools
Classifier: License :: OSI Approved :: Apache Software License
Classifier: Programming Language :: Python :: 2
Classifier: Programming Language :: Python :: 3
